brisket/__init__.py
brisket/brisket.pyd
brisket/brisket.pyi
brisket/brisket.pyx
brisket-0.1.1.dist-info/licenses/LICENSE
brisket-0.1.1.dist-info/METADATA
brisket-0.1.1.dist-info/WHEEL
brisket-0.1.1.dist-info/RECORD
