Metadata-Version: 2.4
Name: brisket
Version: 0.1.1
Summary: Fast Cython-powered one-hot encoding for DNA sequences
License: MIT
License-File: LICENSE
Keywords: bioinformatics,dna,one-hot-encoding,cython,genomics
Author: Natalie Gill
Requires-Python: >=3.9,<4.0
Classifier: Development Status :: 4 - Beta
Classifier: Intended Audience :: Science/Research
Classifier: License :: OSI Approved :: MIT License
Classifier: Programming Language :: Python :: 3
Classifier: Programming Language :: Python :: 3.9
Classifier: Programming Language :: Python :: 3.10
Classifier: Programming Language :: Python :: 3.11
Classifier: Programming Language :: Python :: 3.12
Classifier: Programming Language :: Python :: 3.13
Classifier: Programming Language :: Python :: 3.14
Classifier: Topic :: Scientific/Engineering :: Bio-Informatics
Requires-Dist: numpy (>=1.21,<3.0)
Project-URL: Homepage, https://github.com/gladstone-institutes/brisket
Project-URL: Repository, https://github.com/gladstone-institutes/brisket
